xchainpy_litecoin/__init__.py
xchainpy_litecoin/client.py
xchainpy_litecoin/const.py
xchainpy_litecoin/crypto.py
xchainpy_litecoin/sochain_api.py
xchainpy_litecoin/utils.py
xchainpy_litecoin/models/__init__.py
xchainpy_litecoin/models/client_types.py
xchainpy_litecoin/models/common.py
xchainpy_litecoin-0.2.1.dist-info/LICENSE
xchainpy_litecoin-0.2.1.dist-info/METADATA
xchainpy_litecoin-0.2.1.dist-info/WHEEL
xchainpy_litecoin-0.2.1.dist-info/top_level.txt
xchainpy_litecoin-0.2.1.dist-info/RECORD
