Metadata-Version: 2.1
Name: xchainpy-litecoin
Version: 0.2.1
Summary: Litecoin Module for XChainPy Clients
Home-page: https://github.com/xchainjs/xchainpy-lib/tree/main/xchainpy/xchainpy_litecoin
Author: THORChain
Author-email: 
License: MIT
Keywords: THORChain,XChainpy,xchainpy_litecoin
Platform: UNKNOWN
Classifier: Intended Audience :: Developers
Classifier: Topic :: Software Development :: Libraries :: Python Modules
Classifier: License :: OSI Approved :: MIT License
Classifier: Programming Language :: Python :: 3
Classifier: Programming Language :: Python :: 3.6
Classifier: Programming Language :: Python :: 3.7
Classifier: Programming Language :: Python
License-File: LICENSE
Requires-Dist: bitcoinlib (>=0.5.2)
Requires-Dist: http3 (>=0.6.7)
Requires-Dist: xchainpy-client (>=0.1.6)
Requires-Dist: xchainpy-crypto (>=0.1.7)
Requires-Dist: xchainpy-util (>=0.1.8)
Requires-Dist: bip-utils (>=1.11.1)
